hp_shared/__init__.py
hp_shared/base/_Array.py
hp_shared/base/_Date.py
hp_shared/base/_Function.py
hp_shared/base/_Math.py
hp_shared/base/_Number.py
hp_shared/base/_Object.py
hp_shared/base/_Set.py
hp_shared/base/_String.py
hp_shared/base/__init__.py
hp_shared/base/_console.py
hp_shared/base/base.py
hp_shared/storage/__init__.py
hp_shared/storage/clipboard.py
hp_shared-11.1.2.dist-info/METADATA
hp_shared-11.1.2.dist-info/WHEEL
hp_shared-11.1.2.dist-info/top_level.txt
hp_shared-11.1.2.dist-info/RECORD
