Metadata-Version: 2.1
Name: hp_shared
Version: 11.1.2
License: MIT
Provides-Extra: dev
Requires-Dist: watchdog >=4.0.1 ; extra == 'dev'
